fcl_algorithms/__init__.py
fcl_algorithms/community/__init__.py
fcl_algorithms/community/community_detection.py
fcl_algorithms/community/meiklejohn_finder.py
fcl_algorithms/community/meiklejohn_reductor.py
fcl_algorithms/request/__init__.py
fcl_algorithms/request/find_address.py
fcl_algorithms/request/find_general.py
fcl_algorithms/request/pdf_address.py
fcl_algorithms/request/pdf_general.py
fcl_algorithms/request/request_address_pdf.py
fcl_algorithms/request/request_address_stats.py
fcl_algorithms/request/request_community_pdf.py
fcl_algorithms/request/request_community_stats.py
fcl_algorithms/request/request_crowley.py
fcl_algorithms/request/request_day_pdf.py
fcl_algorithms/request/request_day_stats.py
fcl_algorithms/request/website_data.py
fcl_algorithms/routine/__init__.py
fcl_algorithms/routine/routine_clear.py
fcl_algorithms/routine/routine_community.py
fcl_algorithms/routine/routine_community_reduce.py
fcl_algorithms/routine/routine_community_type.py
fcl_algorithms/routine/routine_data.py
fcl_algorithms/routine/routine_process.py
fcl_algorithms/routine/routine_wallet.py
fcl_algorithms/routine/routine_wallet_type.py
fcl_algorithms/utils/__init__.py
fcl_algorithms/utils/tool_addtags.py
fcl_algorithms/utils/tool_cdetection.py
fcl_algorithms/utils/tool_cinvestigation.py
fcl_algorithms/utils/tool_webgraph.py
fcl_algorithms-0.1.0.dist-info/LICENSE
fcl_algorithms-0.1.0.dist-info/METADATA
fcl_algorithms-0.1.0.dist-info/WHEEL
fcl_algorithms-0.1.0.dist-info/top_level.txt
fcl_algorithms-0.1.0.dist-info/RECORD
