Metadata-Version: 2.1
Name: fcl_algorithms
Version: 0.1.0
Summary: A suite of funcitons to analyse Bitcoin transaction networks and provide the back-end for findcryptolinks.com
Home-page: https://findcryptolinks.com/
Author: Find Crypto Links
Author-email: findcryptolinks@gmail.com
Classifier: Programming Language :: Python :: 3.11
Classifier: License :: OSI Approved :: MIT License
Classifier: Operating System :: OS Independent
Requires-Python: <3.12,>=3.11
License-File: LICENSE
Requires-Dist: networkx ==3.3
Requires-Dist: cdlib ==0.4.0
Requires-Dist: pandas ==2.2.2
Requires-Dist: numpy ==1.26.4
Requires-Dist: fpdf ==1.7.2
Requires-Dist: pydantic >=2.6.2
Requires-Dist: pyyaml >=6.0.1
Requires-Dist: tomli >=2.0.1
Provides-Extra: dev
Requires-Dist: bump2version >=1.0.0 ; extra == 'dev'
Requires-Dist: pre-commit >=2.6.0 ; extra == 'dev'
Requires-Dist: ruff >=0.0.270 ; extra == 'dev'
Requires-Dist: chispa >=0.9.2 ; extra == 'dev'
Requires-Dist: coverage[toml] >=7.1.0 ; extra == 'dev'
Requires-Dist: pytest <8.0.0,>=7.1.0 ; extra == 'dev'
Requires-Dist: pytest-cov >=4.0.0 ; extra == 'dev'
Requires-Dist: pytest-lazy-fixture >=0.6.0 ; extra == 'dev'
Requires-Dist: pytest-mock >=3.8.0 ; extra == 'dev'
Requires-Dist: pyspark ==3.5.1 ; extra == 'dev'
Requires-Dist: moto >=5.0.7 ; extra == 'dev'
Requires-Dist: black >=24.4.2 ; extra == 'dev'
Requires-Dist: isort >=5.13.2 ; extra == 'dev'
Provides-Extra: doc
Requires-Dist: mkdocs >=1.4.2 ; extra == 'doc'
Requires-Dist: mkdocs-tech-docs-template >=0.1.2 ; extra == 'doc'
Requires-Dist: mkdocstrings[python] >=0.22.0 ; extra == 'doc'
Requires-Dist: mkdocs-git-revision-date-localized-plugin >=1.2.1 ; extra == 'doc'
Requires-Dist: mkdocs-jupyter >=0.24.3 ; extra == 'doc'
Requires-Dist: mkdocs-mermaid2-plugin >=1.1.1 ; extra == 'doc'
